exectiming/__init__.py
exectiming/best_fit_curves.py
exectiming/data_structures.py
exectiming/exectiming.py
exectiming/output_wrappers.py
exectiming-2.0.1.dist-info/LICENSE
exectiming-2.0.1.dist-info/METADATA
exectiming-2.0.1.dist-info/WHEEL
exectiming-2.0.1.dist-info/top_level.txt
exectiming-2.0.1.dist-info/RECORD
