Metadata-Version: 2.1
Name: exectiming
Version: 2.0.1
Summary: A Python module for measuring the execution time of code
Home-page: https://github.com/blendingjake/exectiming
Author: Jacob Morris
Author-email: blendingjake@gmail.com
License: UNKNOWN
Platform: UNKNOWN
Classifier: Programming Language :: Python :: 3
Classifier: License :: OSI Approved :: GNU General Public License v3 (GPLv3)
Classifier: Operating System :: OS Independent
Classifier: Topic :: Software Development :: Testing
Requires-Python: >=3.3
Requires-Dist: scikit-learn
Requires-Dist: scipy
Requires-Dist: numpy
Requires-Dist: matplotlib
